{
   "date": {
      "ui:field": "rdp",
      "rdp": {
        "dayPickerProps": {
          "todayButton": "Today"
         }
      }
   },
   "assignmentDate": {
      "ui:field": "rdp",
      "rdp": {
        "dayPickerProps": {
          "todayButton": "Today"
         }
      }
   },
   "boolean": {
      "radio": {
        "ui:widget": "radio"
      },
      "select": {
        "ui:widget": "select"
      }
   },
   "listOfStrings": {
      "items": {
        "ui:emptyValue": ""
      }
   },
   "assignmentPercentage": {
      "ui:widget": "range"
   },
   "arrayOfConditionals": {
      "items": {
        "Do you want to get rid of any?": {
          "ui:widget": "radio"
        }
      }
    }
}
